<?xml version="1.0"?>
<opencv_storage>
<hog type_id="opencv-object-detector-hog">
  <winSize>
    32 32</winSize>
  <blockSize>
    16 16</blockSize>
  <blockStride>
    8 8</blockStride>
  <cellSize>
    8 8</cellSize>
  <nbins>9</nbins>
  <derivAperture>1</derivAperture>
  <winSigma>4.</winSigma>
  <histogramNormType>0</histogramNormType>
  <L2HysThreshold>2.0000000000000001e-01</L2HysThreshold>
  <gammaCorrection>1</gammaCorrection>
  <nlevels>64</nlevels>
  <signedGradient>0</signedGradient></hog>
</opencv_storage>
